helics_cli_extras/__init__.py
helics_cli_extras/database.py
helics_cli_extras/flask_app.py
helics_cli_extras/observer.py
helics_cli_extras/static/favicon.png
helics_cli_extras/static/index.html
helics_cli_extras/static/_app/env.js
helics_cli_extras/static/_app/version.json
helics_cli_extras/static/_app/immutable/assets/0.CL1elfqe.css
helics_cli_extras/static/_app/immutable/assets/5.CurIzjok.css
helics_cli_extras/static/_app/immutable/assets/Dropzone.D3Z5rp1S.css
helics_cli_extras/static/_app/immutable/assets/ScaledSvg.DAiRe3NN.css
helics_cli_extras/static/_app/immutable/assets/fa-layers-text.ZJaHuitq.css
helics_cli_extras/static/_app/immutable/chunks/BGP0akLM.js
helics_cli_extras/static/_app/immutable/chunks/Bypr0-Js.js
helics_cli_extras/static/_app/immutable/chunks/C0R47HOl.js
helics_cli_extras/static/_app/immutable/chunks/C8Jx7AEg.js
helics_cli_extras/static/_app/immutable/chunks/C8zSuf0b.js
helics_cli_extras/static/_app/immutable/chunks/CCFLHyNb.js
helics_cli_extras/static/_app/immutable/chunks/CIEyhB0e.js
helics_cli_extras/static/_app/immutable/chunks/COjgeFWH.js
helics_cli_extras/static/_app/immutable/chunks/CcwB7Tjh.js
helics_cli_extras/static/_app/immutable/chunks/CdQeho8k.js
helics_cli_extras/static/_app/immutable/chunks/D0ky-wp8.js
helics_cli_extras/static/_app/immutable/chunks/D2iqoFGv.js
helics_cli_extras/static/_app/immutable/chunks/DcsVdkUI.js
helics_cli_extras/static/_app/immutable/chunks/DeHn-c2i.js
helics_cli_extras/static/_app/immutable/chunks/DfmVMWXE.js
helics_cli_extras/static/_app/immutable/chunks/Dp1pzeXC.js
helics_cli_extras/static/_app/immutable/chunks/DvaMvQ_S.js
helics_cli_extras/static/_app/immutable/chunks/DxqtznRv.js
helics_cli_extras/static/_app/immutable/chunks/FF3P85hg.js
helics_cli_extras/static/_app/immutable/chunks/cZ5dS-Bk.js
helics_cli_extras/static/_app/immutable/chunks/piPHs14J.js
helics_cli_extras/static/_app/immutable/entry/app.DqmT3bH1.js
helics_cli_extras/static/_app/immutable/entry/start.C4-S89ey.js
helics_cli_extras-0.0.2.dist-info/METADATA
helics_cli_extras-0.0.2.dist-info/WHEEL
helics_cli_extras-0.0.2.dist-info/top_level.txt
helics_cli_extras-0.0.2.dist-info/RECORD
