Metadata-Version: 2.1
Name: helics-cli-extras
Version: 0.0.2
Summary: Python HELICS bindings
Author-email: Dheepak Krishnamurthy <me@kdheepak.com>
Maintainer-email: Dheepak Krishnamurthy <me@kdheepak.com>, Ryan Mast <mast9@llnl.gov>
License: MIT License
Project-URL: Homepage, https://github.com/GMLC-TDC/pyhelics
Project-URL: Discussions, https://github.com/GMLC-TDC/HELICS/discussions
Project-URL: Documentation, https://python.helics.org/
Project-URL: Issue Tracker, https://github.com/GMLC-TDC/pyhelics/issues
Project-URL: Source Code, https://github.com/GMLC-TDC/pyhelics
Keywords: helics,co-simulation,webserver
Classifier: Development Status :: 5 - Production/Stable
Classifier: Intended Audience :: Developers
Classifier: License :: OSI Approved :: MIT License
Classifier: Operating System :: Unix
Classifier: Operating System :: POSIX
Classifier: Operating System :: POSIX :: Linux
Classifier: Operating System :: MacOS
Classifier: Operating System :: Microsoft :: Windows
Classifier: Environment :: Console
Classifier: Programming Language :: Python
Classifier: Programming Language :: Python :: 3
Classifier: Programming Language :: Python :: 3 :: Only
Classifier: Programming Language :: Python :: 3.6
Classifier: Programming Language :: Python :: 3.7
Classifier: Programming Language :: Python :: 3.8
Classifier: Programming Language :: Python :: 3.9
Classifier: Programming Language :: Python :: 3.10
Classifier: Programming Language :: Python :: 3.11
Classifier: Programming Language :: Python :: 3.12
Classifier: Programming Language :: Python :: Implementation :: CPython
Classifier: Programming Language :: Python :: Implementation :: PyPy
Classifier: Topic :: Utilities
Classifier: Topic :: Software Development
Requires-Python: >=3.6
Requires-Dist: flask>=2
Requires-Dist: requests
Requires-Dist: flask-restful
Requires-Dist: flask-cors
Requires-Dist: pandas
Requires-Dist: SQLAlchemy
